twint/__init__.py
twint/__main__.py
twint/__version__.py
twint/cli.py
twint/config.py
twint/datelock.py
twint/feed.py
twint/format.py
twint/get.py
twint/output.py
twint/run.py
twint/token.py
twint/tweet.py
twint/url.py
twint/user.py
twint/verbose.py
twint/storage/__init__.py
twint/storage/db.py
twint/storage/elasticsearch.py
twint/storage/panda.py
twint/storage/write.py
twint/storage/write_meta.py
twint_fork-2.5.3.dist-info/LICENSE
twint_fork-2.5.3.dist-info/METADATA
twint_fork-2.5.3.dist-info/WHEEL
twint_fork-2.5.3.dist-info/dependency_links.txt
twint_fork-2.5.3.dist-info/entry_points.txt
twint_fork-2.5.3.dist-info/top_level.txt
twint_fork-2.5.3.dist-info/RECORD
