Metadata-Version: 2.1
Name: twint-fork
Version: 2.5.3
Summary: An advanced Twitter scraping & OSINT tool.
Home-page: https://github.com/yihong0618/twint
Author: Cody Zacharias, yihong0618
Author-email: codyzacharias@pm.me, zouzou0208@gmail.com
License: MIT
Classifier: License :: OSI Approved :: MIT License
Classifier: Programming Language :: Python
Classifier: Programming Language :: Python :: 3
Classifier: Programming Language :: Python :: 3.7
Classifier: Programming Language :: Python :: 3.8
Classifier: Programming Language :: Python :: 3.9
Classifier: Programming Language :: Python :: 3.10
Classifier: Programming Language :: Python :: 3.11
Classifier: Programming Language :: Python :: Implementation :: CPython
Requires-Python: >=3.7.0
License-File: LICENSE
Requires-Dist: aiohttp
Requires-Dist: aiodns
Requires-Dist: beautifulsoup4
Requires-Dist: cchardet
Requires-Dist: dataclasses
Requires-Dist: elasticsearch
Requires-Dist: pysocks
Requires-Dist: pandas
Requires-Dist: aiohttp-socks
Requires-Dist: schedule
Requires-Dist: geopy
Requires-Dist: fake-useragent
Requires-Dist: googletransx
Requires-Dist: rich
